dms_influx2/__init__.py
dms_influx2/authorizations.py
dms_influx2/buckets.py
dms_influx2/checks.py
dms_influx2/decorators.py
dms_influx2/delete.py
dms_influx2/dtv_files.py
dms_influx2/exceptions.py
dms_influx2/lib.py
dms_influx2/notifications.py
dms_influx2/organisations.py
dms_influx2/query.py
dms_influx2/sync.py
dms_influx2/tasks.py
dms_influx2/utils.py
dms_influx2-0.4.0.dist-info/METADATA
dms_influx2-0.4.0.dist-info/WHEEL
dms_influx2-0.4.0.dist-info/top_level.txt
dms_influx2-0.4.0.dist-info/RECORD
