Metadata-Version: 2.1
Name: dms-influx2
Version: 0.4.0
Summary: Library to connect and retrieve data from DMS influxdb
Home-page: https://github.com/belingarb/dms-influx2
Author: Bozidar Belingar
Author-email: bozidar.belingar@gmail.com
License: MIT
Classifier: License :: OSI Approved :: BSD License
Classifier: Programming Language :: Python :: 3.8
Classifier: Programming Language :: Python :: Implementation :: PyPy
Requires-Python: >=3.8.0
Requires-Dist: ciso8601 (==2.3.0)
Requires-Dist: influxdb-client (==1.36.1)
Requires-Dist: python-dateutil (~=2.8.1)
Requires-Dist: tzlocal (==4.3)
Requires-Dist: pytz (==2023.3)
